CHANGES.txt
LICENSE.txt
MANIFEST.in
README.rst
setup.py
js/__init__.py
js.amcharts.egg-info/PKG-INFO
js.amcharts.egg-info/SOURCES.txt
js.amcharts.egg-info/dependency_links.txt
js.amcharts.egg-info/entry_points.txt
js.amcharts.egg-info/namespace_packages.txt
js.amcharts.egg-info/not-zip-safe
js.amcharts.egg-info/requires.txt
js.amcharts.egg-info/top_level.txt
js/amcharts/__init__.py
js/amcharts/test_amcharts.txt
js/amcharts/resources/amcharts.js
js/amcharts/resources/amstock.js
js/amcharts/resources/changeLog.txt
js/amcharts/resources/licence.txt
js/amcharts/resources/serial.js
js/amcharts/resources/style.css
js/amcharts/resources/thirdPartySoftwareList.txt
js/amcharts/resources/exporting/amexport.js
js/amcharts/resources/exporting/canvg.js
js/amcharts/resources/exporting/filesaver.js
js/amcharts/resources/exporting/jspdf.js
js/amcharts/resources/exporting/jspdf.plugin.addimage.js
js/amcharts/resources/exporting/rgbcolor.js
js/amcharts/resources/images/dragIcon.gif
js/amcharts/resources/images/dragIconH.gif
js/amcharts/resources/images/eraserIcon.gif
js/amcharts/resources/images/eraserIconH.gif
js/amcharts/resources/images/export.png
js/amcharts/resources/images/lens.png
js/amcharts/resources/images/pencilIcon.gif
js/amcharts/resources/images/pencilIconH.gif
js/amcharts/resources/images/xIcon.gif
js/amcharts/resources/images/xIconH.gif
js/amcharts/resources/patterns/black/pattern1.png
js/amcharts/resources/patterns/black/pattern10.png
js/amcharts/resources/patterns/black/pattern11.png
js/amcharts/resources/patterns/black/pattern12.png
js/amcharts/resources/patterns/black/pattern13.png
js/amcharts/resources/patterns/black/pattern14.png
js/amcharts/resources/patterns/black/pattern15.png
js/amcharts/resources/patterns/black/pattern16.png
js/amcharts/resources/patterns/black/pattern17.png
js/amcharts/resources/patterns/black/pattern18.png
js/amcharts/resources/patterns/black/pattern19.png
js/amcharts/resources/patterns/black/pattern2.png
js/amcharts/resources/patterns/black/pattern20.png
js/amcharts/resources/patterns/black/pattern21.png
js/amcharts/resources/patterns/black/pattern3.png
js/amcharts/resources/patterns/black/pattern4.png
js/amcharts/resources/patterns/black/pattern5.png
js/amcharts/resources/patterns/black/pattern6.png
