Metadata-Version: 1.0
Name: js.amcharts
Version: 3.3.1
Summary: Fanstatic packaging of amCharts
Home-page: https://github.com/securactive/js.amcharts
Author: Fanstatic Developers
Author-email: fanstatic@googlegroups.com
License: BSD
Platform: UNKNOWN
